Syncra/__init__.py
Syncra/main.py
Syncraa-1.6.1.dist-info/LICENSE
Syncraa-1.6.1.dist-info/METADATA
Syncraa-1.6.1.dist-info/WHEEL
Syncraa-1.6.1.dist-info/entry_points.txt
Syncraa-1.6.1.dist-info/top_level.txt
Syncraa-1.6.1.dist-info/RECORD
