Metadata-Version: 2.1
Name: Syncraa
Version: 1.6.1
Summary: A tool to manage Plex playlists and import from streaming services
Home-page: https://github.com/jaylex32/Syncra
Author: jaylex32
Author-email: jayrossproduction@gmail.com
Classifier: Programming Language :: Python :: 3
Classifier: License :: OSI Approved :: MIT License
Classifier: Operating System :: OS Independent
Requires-Python: >=3.6
License-File: LICENSE
Requires-Dist: PyQt5
Requires-Dist: plexapi
Requires-Dist: spotipy
Requires-Dist: deezer-python
Requires-Dist: requests
Requires-Dist: fuzzywuzzy
